{
  "pluginId": "LibraryComponentPlugin",
  "id": "library-component-drop-symphony",
  "name": "Library Component Drop",
  "movements": [
    {
      "id": "drop",
      "name": "Drop",
      "beats": [
        {
          "beat": 1,
          "event": "library:component:drop",
          "title": "Publish Create Requested",
          "dynamics": "mf",
          "handler": "publishCreateRequested",
          "timing": "immediate",
          "kind": "pure",
          "scenario": "Publish or Deploy publish Create Requested",
          "userStory": "As an orchestrator, I need `publishCreateRequested` to forward to canvas-component create.",
          "testCase": "forwards to drop symphony and does not render React nodes directly",
          "testFile": "node_modules\\@renderx-plugins\\canvas\\__tests__\\create-page.dom.spec.ts",
          "acceptanceCriteriaStructured": [
            {
              "given": [
                "valid drop target"
              ],
              "when": [
                "onDrop runs"
              ],
              "then": [
                "composes node and validates schema; latency ≤ 150ms"
              ],
              "and": [
                "telemetry 'drop' includes target and success"
              ]
            }
          ]
        }
      ],
      "userStory": "As an interaction designer, I need drop to publish create requests deterministically and clear preview state.",
      "persona": "Interaction designer",
      "businessValue": "Enables automated deployment; reduces release cycle time by 70%; improves availability (target: 99.9%); supports CI/CD"
    }
  ],
  "beats": 1,
  "userStory": "As an interaction designer, I need drop to publish create requests deterministically and clear preview state.",
  "persona": "Interaction designer",
  "businessValue": "Enables automated deployment; reduces release cycle time by 70%; improves availability (target: 99.9%); supports CI/CD",
  "domainId": "renderx-web-orchestration"
}
