{
  "timestamp": "2025-11-24T20:31:16.485Z",
  "version": "1.0.0",
  "totalFiles": 35,
  "byCategory": {
    "generated-index": [
      {
        "filename": "DOC_INDEX.json",
        "sourceLocation": ".",
        "classification": "generated-index",
        "domain": null,
        "reason": "Generated documentation index",
        "targetLocation": "docs/search",
        "shouldMove": true,
        "action": "move",
        "fullSourcePath": "C:\\source\\repos\\bpm\\internal\\renderx-plugins-demo\\DOC_INDEX.json",
        "fullTargetPath": "C:\\source\\repos\\bpm\\internal\\renderx-plugins-demo\\docs\\search\\DOC_INDEX.json"
      },
      {
        "filename": "knowledge-index.json",
        "sourceLocation": ".",
        "classification": "generated-index",
        "domain": null,
        "reason": "Generated knowledge index",
        "targetLocation": "docs/search",
        "shouldMove": true,
        "action": "move",
        "fullSourcePath": "C:\\source\\repos\\bpm\\internal\\renderx-plugins-demo\\knowledge-index.json",
        "fullTargetPath": "C:\\source\\repos\\bpm\\internal\\renderx-plugins-demo\\docs\\search\\knowledge-index.json"
      }
    ],
    "governance": [
      {
        "filename": "PROJECT_BOUNDARIES.json",
        "sourceLocation": ".",
        "classification": "governance",
        "domain": null,
        "reason": "CONFIG: Project metadata",
        "targetLocation": "docs/governance",
        "shouldMove": true,
        "action": "move",
        "fullSourcePath": "C:\\source\\repos\\bpm\\internal\\renderx-plugins-demo\\PROJECT_BOUNDARIES.json",
        "fullTargetPath": "C:\\source\\repos\\bpm\\internal\\renderx-plugins-demo\\docs\\governance\\PROJECT_BOUNDARIES.json"
      },
      {
        "filename": "PROJECT_ROLES.json",
        "sourceLocation": ".",
        "classification": "governance",
        "domain": null,
        "reason": "CONFIG: Project metadata",
        "targetLocation": "docs/governance",
        "shouldMove": true,
        "action": "move",
        "fullSourcePath": "C:\\source\\repos\\bpm\\internal\\renderx-plugins-demo\\PROJECT_ROLES.json",
        "fullTargetPath": "C:\\source\\repos\\bpm\\internal\\renderx-plugins-demo\\docs\\governance\\PROJECT_ROLES.json"
      },
      {
        "filename": "PROJECT_SCOPE.json",
        "sourceLocation": ".",
        "classification": "governance",
        "domain": null,
        "reason": "CONFIG: Project metadata",
        "targetLocation": "docs/governance",
        "shouldMove": true,
        "action": "move",
        "fullSourcePath": "C:\\source\\repos\\bpm\\internal\\renderx-plugins-demo\\PROJECT_SCOPE.json",
        "fullTargetPath": "C:\\source\\repos\\bpm\\internal\\renderx-plugins-demo\\docs\\governance\\PROJECT_SCOPE.json"
      },
      {
        "filename": "PROJECT_TAGS.json",
        "sourceLocation": ".",
        "classification": "governance",
        "domain": null,
        "reason": "CONFIG: Project metadata",
        "targetLocation": "docs/governance",
        "shouldMove": true,
        "action": "move",
        "fullSourcePath": "C:\\source\\repos\\bpm\\internal\\renderx-plugins-demo\\PROJECT_TAGS.json",
        "fullTargetPath": "C:\\source\\repos\\bpm\\internal\\renderx-plugins-demo\\docs\\governance\\PROJECT_TAGS.json"
      },
      {
        "filename": "orchestration-audit-system-project-plan.json",
        "sourceLocation": ".",
        "classification": "governance",
        "domain": null,
        "reason": "AUTHORITY: Project plan",
        "targetLocation": "docs/governance",
        "shouldMove": true,
        "action": "move",
        "fullSourcePath": "C:\\source\\repos\\bpm\\internal\\renderx-plugins-demo\\orchestration-audit-system-project-plan.json",
        "fullTargetPath": "C:\\source\\repos\\bpm\\internal\\renderx-plugins-demo\\docs\\governance\\orchestration-audit-system-project-plan.json"
      },
      {
        "filename": "orchestration-domains.json",
        "sourceLocation": ".",
        "classification": "governance",
        "domain": null,
        "reason": "CONFIG: Domain mapping",
        "targetLocation": "docs/governance",
        "shouldMove": true,
        "action": "move",
        "fullSourcePath": "C:\\source\\repos\\bpm\\internal\\renderx-plugins-demo\\orchestration-domains.json",
        "fullTargetPath": "C:\\source\\repos\\bpm\\internal\\renderx-plugins-demo\\docs\\governance\\orchestration-domains.json"
      }
    ],
    "domain-config": [
      {
        "filename": "REACT_COMPONENT_SELECTION_TRACE.json",
        "sourceLocation": ".",
        "classification": "domain-config",
        "domain": "react",
        "reason": "React component configuration",
        "targetLocation": "docs/react",
        "shouldMove": true,
        "action": "move",
        "fullSourcePath": "C:\\source\\repos\\bpm\\internal\\renderx-plugins-demo\\REACT_COMPONENT_SELECTION_TRACE.json",
        "fullTargetPath": "C:\\source\\repos\\bpm\\internal\\renderx-plugins-demo\\docs\\react\\REACT_COMPONENT_SELECTION_TRACE.json"
      },
      {
        "filename": "SHAPE_EVOLUTION_PLAN.json",
        "sourceLocation": ".",
        "classification": "domain-config",
        "domain": "shape",
        "reason": "Shape/evolution configuration",
        "targetLocation": "docs/shape",
        "shouldMove": true,
        "action": "move",
        "fullSourcePath": "C:\\source\\repos\\bpm\\internal\\renderx-plugins-demo\\SHAPE_EVOLUTION_PLAN.json",
        "fullTargetPath": "C:\\source\\repos\\bpm\\internal\\renderx-plugins-demo\\docs\\shape\\SHAPE_EVOLUTION_PLAN.json"
      },
      {
        "filename": "react-component-context-with-publish.json",
        "sourceLocation": ".",
        "classification": "domain-config",
        "domain": "react",
        "reason": "React component configuration",
        "targetLocation": "docs/react",
        "shouldMove": true,
        "action": "move",
        "fullSourcePath": "C:\\source\\repos\\bpm\\internal\\renderx-plugins-demo\\react-component-context-with-publish.json",
        "fullTargetPath": "C:\\source\\repos\\bpm\\internal\\renderx-plugins-demo\\docs\\react\\react-component-context-with-publish.json"
      },
      {
        "filename": "react-component-context.json",
        "sourceLocation": ".",
        "classification": "domain-config",
        "domain": "react",
        "reason": "React component configuration",
        "targetLocation": "docs/react",
        "shouldMove": true,
        "action": "move",
        "fullSourcePath": "C:\\source\\repos\\bpm\\internal\\renderx-plugins-demo\\react-component-context.json",
        "fullTargetPath": "C:\\source\\repos\\bpm\\internal\\renderx-plugins-demo\\docs\\react\\react-component-context.json"
      },
      {
        "filename": "react-component-theme-toggle.json",
        "sourceLocation": ".",
        "classification": "domain-config",
        "domain": "react",
        "reason": "React component configuration",
        "targetLocation": "docs/react",
        "shouldMove": true,
        "action": "move",
        "fullSourcePath": "C:\\source\\repos\\bpm\\internal\\renderx-plugins-demo\\react-component-theme-toggle.json",
        "fullTargetPath": "C:\\source\\repos\\bpm\\internal\\renderx-plugins-demo\\docs\\react\\react-component-theme-toggle.json"
      },
      {
        "filename": "shape-evolutions-allowlist.json",
        "sourceLocation": ".",
        "classification": "domain-config",
        "domain": "shape",
        "reason": "Shape/evolution configuration",
        "targetLocation": "docs/shape",
        "shouldMove": true,
        "action": "move",
        "fullSourcePath": "C:\\source\\repos\\bpm\\internal\\renderx-plugins-demo\\shape-evolutions-allowlist.json",
        "fullTargetPath": "C:\\source\\repos\\bpm\\internal\\renderx-plugins-demo\\docs\\shape\\shape-evolutions-allowlist.json"
      },
      {
        "filename": "shape-evolutions.json",
        "sourceLocation": ".",
        "classification": "domain-config",
        "domain": "shape",
        "reason": "Shape/evolution configuration",
        "targetLocation": "docs/shape",
        "shouldMove": true,
        "action": "move",
        "fullSourcePath": "C:\\source\\repos\\bpm\\internal\\renderx-plugins-demo\\shape-evolutions.json",
        "fullTargetPath": "C:\\source\\repos\\bpm\\internal\\renderx-plugins-demo\\docs\\shape\\shape-evolutions.json"
      },
      {
        "filename": "shape.budgets.json",
        "sourceLocation": ".",
        "classification": "domain-config",
        "domain": "shape",
        "reason": "Shape/evolution configuration",
        "targetLocation": "docs/shape",
        "shouldMove": true,
        "action": "move",
        "fullSourcePath": "C:\\source\\repos\\bpm\\internal\\renderx-plugins-demo\\shape.budgets.json",
        "fullTargetPath": "C:\\source\\repos\\bpm\\internal\\renderx-plugins-demo\\docs\\shape\\shape.budgets.json"
      }
    ],
    "generated-data": [
      {
        "filename": "canvas_symphony_data.json",
        "sourceLocation": ".",
        "classification": "generated-data",
        "domain": null,
        "reason": "Generated symphony data",
        "targetLocation": "docs/search",
        "shouldMove": true,
        "action": "move",
        "fullSourcePath": "C:\\source\\repos\\bpm\\internal\\renderx-plugins-demo\\canvas_symphony_data.json",
        "fullTargetPath": "C:\\source\\repos\\bpm\\internal\\renderx-plugins-demo\\docs\\search\\canvas_symphony_data.json"
      }
    ],
    "unclassified": [
      {
        "filename": "derived-external-interactions.json",
        "sourceLocation": ".",
        "classification": "unclassified",
        "domain": null,
        "reason": "Unclassified JSON file",
        "targetLocation": ".generated",
        "shouldMove": true,
        "action": "move",
        "fullSourcePath": "C:\\source\\repos\\bpm\\internal\\renderx-plugins-demo\\derived-external-interactions.json",
        "fullTargetPath": "C:\\source\\repos\\bpm\\internal\\renderx-plugins-demo\\.generated\\derived-external-interactions.json"
      },
      {
        "filename": "derived-external-topics.json",
        "sourceLocation": ".",
        "classification": "unclassified",
        "domain": null,
        "reason": "Unclassified JSON file",
        "targetLocation": ".generated",
        "shouldMove": true,
        "action": "move",
        "fullSourcePath": "C:\\source\\repos\\bpm\\internal\\renderx-plugins-demo\\derived-external-topics.json",
        "fullTargetPath": "C:\\source\\repos\\bpm\\internal\\renderx-plugins-demo\\.generated\\derived-external-topics.json"
      },
      {
        "filename": "eslint-report.json",
        "sourceLocation": ".",
        "classification": "unclassified",
        "domain": null,
        "reason": "Unclassified JSON file",
        "targetLocation": ".generated",
        "shouldMove": true,
        "action": "move",
        "fullSourcePath": "C:\\source\\repos\\bpm\\internal\\renderx-plugins-demo\\eslint-report.json",
        "fullTargetPath": "C:\\source\\repos\\bpm\\internal\\renderx-plugins-demo\\.generated\\eslint-report.json"
      },
      {
        "filename": "eslint-report3.json",
        "sourceLocation": ".",
        "classification": "unclassified",
        "domain": null,
        "reason": "Unclassified JSON file",
        "targetLocation": ".generated",
        "shouldMove": true,
        "action": "move",
        "fullSourcePath": "C:\\source\\repos\\bpm\\internal\\renderx-plugins-demo\\eslint-report3.json",
        "fullTargetPath": "C:\\source\\repos\\bpm\\internal\\renderx-plugins-demo\\.generated\\eslint-report3.json"
      },
      {
        "filename": "eslint-report4.json",
        "sourceLocation": ".",
        "classification": "unclassified",
        "domain": null,
        "reason": "Unclassified JSON file",
        "targetLocation": ".generated",
        "shouldMove": true,
        "action": "move",
        "fullSourcePath": "C:\\source\\repos\\bpm\\internal\\renderx-plugins-demo\\eslint-report4.json",
        "fullTargetPath": "C:\\source\\repos\\bpm\\internal\\renderx-plugins-demo\\.generated\\eslint-report4.json"
      },
      {
        "filename": "eslint-report5.json",
        "sourceLocation": ".",
        "classification": "unclassified",
        "domain": null,
        "reason": "Unclassified JSON file",
        "targetLocation": ".generated",
        "shouldMove": true,
        "action": "move",
        "fullSourcePath": "C:\\source\\repos\\bpm\\internal\\renderx-plugins-demo\\eslint-report5.json",
        "fullTargetPath": "C:\\source\\repos\\bpm\\internal\\renderx-plugins-demo\\.generated\\eslint-report5.json"
      },
      {
        "filename": "eslint-report6.json",
        "sourceLocation": ".",
        "classification": "unclassified",
        "domain": null,
        "reason": "Unclassified JSON file",
        "targetLocation": ".generated",
        "shouldMove": true,
        "action": "move",
        "fullSourcePath": "C:\\source\\repos\\bpm\\internal\\renderx-plugins-demo\\eslint-report6.json",
        "fullTargetPath": "C:\\source\\repos\\bpm\\internal\\renderx-plugins-demo\\.generated\\eslint-report6.json"
      },
      {
        "filename": "eslint-report7.json",
        "sourceLocation": ".",
        "classification": "unclassified",
        "domain": null,
        "reason": "Unclassified JSON file",
        "targetLocation": ".generated",
        "shouldMove": true,
        "action": "move",
        "fullSourcePath": "C:\\source\\repos\\bpm\\internal\\renderx-plugins-demo\\eslint-report7.json",
        "fullTargetPath": "C:\\source\\repos\\bpm\\internal\\renderx-plugins-demo\\.generated\\eslint-report7.json"
      },
      {
        "filename": "eslint-report8.json",
        "sourceLocation": ".",
        "classification": "unclassified",
        "domain": null,
        "reason": "Unclassified JSON file",
        "targetLocation": ".generated",
        "shouldMove": true,
        "action": "move",
        "fullSourcePath": "C:\\source\\repos\\bpm\\internal\\renderx-plugins-demo\\eslint-report8.json",
        "fullTargetPath": "C:\\source\\repos\\bpm\\internal\\renderx-plugins-demo\\.generated\\eslint-report8.json"
      }
    ],
    "manifests": [
      {
        "filename": "interaction-manifest.json",
        "sourceLocation": ".",
        "classification": "manifests",
        "domain": null,
        "reason": "Plugin/layout manifest",
        "targetLocation": "docs/manifests",
        "shouldMove": true,
        "action": "move",
        "fullSourcePath": "C:\\source\\repos\\bpm\\internal\\renderx-plugins-demo\\interaction-manifest.json",
        "fullTargetPath": "C:\\source\\repos\\bpm\\internal\\renderx-plugins-demo\\docs\\manifests\\interaction-manifest.json"
      },
      {
        "filename": "layout-manifest.json",
        "sourceLocation": ".",
        "classification": "manifests",
        "domain": null,
        "reason": "Plugin/layout manifest",
        "targetLocation": "docs/manifests",
        "shouldMove": true,
        "action": "move",
        "fullSourcePath": "C:\\source\\repos\\bpm\\internal\\renderx-plugins-demo\\layout-manifest.json",
        "fullTargetPath": "C:\\source\\repos\\bpm\\internal\\renderx-plugins-demo\\docs\\manifests\\layout-manifest.json"
      },
      {
        "filename": "topics-manifest.json",
        "sourceLocation": ".",
        "classification": "manifests",
        "domain": null,
        "reason": "Plugin/layout manifest",
        "targetLocation": "docs/manifests",
        "shouldMove": true,
        "action": "move",
        "fullSourcePath": "C:\\source\\repos\\bpm\\internal\\renderx-plugins-demo\\topics-manifest.json",
        "fullTargetPath": "C:\\source\\repos\\bpm\\internal\\renderx-plugins-demo\\docs\\manifests\\topics-manifest.json"
      }
    ],
    "build-config": [
      {
        "filename": "package-lock.json",
        "sourceLocation": ".",
        "classification": "build-config",
        "domain": null,
        "reason": "Build/runtime configuration",
        "targetLocation": ".",
        "shouldMove": false,
        "action": "keep-in-root",
        "fullSourcePath": "C:\\source\\repos\\bpm\\internal\\renderx-plugins-demo\\package-lock.json",
        "fullTargetPath": "C:\\source\\repos\\bpm\\internal\\renderx-plugins-demo\\package-lock.json"
      },
      {
        "filename": "package.json",
        "sourceLocation": ".",
        "classification": "build-config",
        "domain": null,
        "reason": "Build/runtime configuration",
        "targetLocation": ".",
        "shouldMove": false,
        "action": "keep-in-root",
        "fullSourcePath": "C:\\source\\repos\\bpm\\internal\\renderx-plugins-demo\\package.json",
        "fullTargetPath": "C:\\source\\repos\\bpm\\internal\\renderx-plugins-demo\\package.json"
      },
      {
        "filename": "tsconfig.base.json",
        "sourceLocation": ".",
        "classification": "build-config",
        "domain": null,
        "reason": "Build/runtime configuration",
        "targetLocation": ".",
        "shouldMove": false,
        "action": "keep-in-root",
        "fullSourcePath": "C:\\source\\repos\\bpm\\internal\\renderx-plugins-demo\\tsconfig.base.json",
        "fullTargetPath": "C:\\source\\repos\\bpm\\internal\\renderx-plugins-demo\\tsconfig.base.json"
      },
      {
        "filename": "tsconfig.json",
        "sourceLocation": ".",
        "classification": "build-config",
        "domain": null,
        "reason": "Build/runtime configuration",
        "targetLocation": ".",
        "shouldMove": false,
        "action": "keep-in-root",
        "fullSourcePath": "C:\\source\\repos\\bpm\\internal\\renderx-plugins-demo\\tsconfig.json",
        "fullTargetPath": "C:\\source\\repos\\bpm\\internal\\renderx-plugins-demo\\tsconfig.json"
      }
    ],
    "generated-hash": [
      {
        "filename": "public-api.hash.json",
        "sourceLocation": ".",
        "classification": "generated-hash",
        "domain": null,
        "reason": "Generated API hash",
        "targetLocation": "docs/search",
        "shouldMove": true,
        "action": "move",
        "fullSourcePath": "C:\\source\\repos\\bpm\\internal\\renderx-plugins-demo\\public-api.hash.json",
        "fullTargetPath": "C:\\source\\repos\\bpm\\internal\\renderx-plugins-demo\\docs\\search\\public-api.hash.json"
      }
    ],
    "generated-context": [
      {
        "filename": "root-context.json",
        "sourceLocation": ".",
        "classification": "generated-context",
        "domain": null,
        "reason": "Generated context",
        "targetLocation": "docs/search",
        "shouldMove": true,
        "action": "move",
        "fullSourcePath": "C:\\source\\repos\\bpm\\internal\\renderx-plugins-demo\\root-context.json",
        "fullTargetPath": "C:\\source\\repos\\bpm\\internal\\renderx-plugins-demo\\docs\\search\\root-context.json"
      }
    ]
  },
  "byAction": {
    "move": [
      {
        "filename": "DOC_INDEX.json",
        "sourceLocation": ".",
        "classification": "generated-index",
        "domain": null,
        "reason": "Generated documentation index",
        "targetLocation": "docs/search",
        "shouldMove": true,
        "action": "move",
        "fullSourcePath": "C:\\source\\repos\\bpm\\internal\\renderx-plugins-demo\\DOC_INDEX.json",
        "fullTargetPath": "C:\\source\\repos\\bpm\\internal\\renderx-plugins-demo\\docs\\search\\DOC_INDEX.json"
      },
      {
        "filename": "PROJECT_BOUNDARIES.json",
        "sourceLocation": ".",
        "classification": "governance",
        "domain": null,
        "reason": "CONFIG: Project metadata",
        "targetLocation": "docs/governance",
        "shouldMove": true,
        "action": "move",
        "fullSourcePath": "C:\\source\\repos\\bpm\\internal\\renderx-plugins-demo\\PROJECT_BOUNDARIES.json",
        "fullTargetPath": "C:\\source\\repos\\bpm\\internal\\renderx-plugins-demo\\docs\\governance\\PROJECT_BOUNDARIES.json"
      },
      {
        "filename": "PROJECT_ROLES.json",
        "sourceLocation": ".",
        "classification": "governance",
        "domain": null,
        "reason": "CONFIG: Project metadata",
        "targetLocation": "docs/governance",
        "shouldMove": true,
        "action": "move",
        "fullSourcePath": "C:\\source\\repos\\bpm\\internal\\renderx-plugins-demo\\PROJECT_ROLES.json",
        "fullTargetPath": "C:\\source\\repos\\bpm\\internal\\renderx-plugins-demo\\docs\\governance\\PROJECT_ROLES.json"
      },
      {
        "filename": "PROJECT_SCOPE.json",
        "sourceLocation": ".",
        "classification": "governance",
        "domain": null,
        "reason": "CONFIG: Project metadata",
        "targetLocation": "docs/governance",
        "shouldMove": true,
        "action": "move",
        "fullSourcePath": "C:\\source\\repos\\bpm\\internal\\renderx-plugins-demo\\PROJECT_SCOPE.json",
        "fullTargetPath": "C:\\source\\repos\\bpm\\internal\\renderx-plugins-demo\\docs\\governance\\PROJECT_SCOPE.json"
      },
      {
        "filename": "PROJECT_TAGS.json",
        "sourceLocation": ".",
        "classification": "governance",
        "domain": null,
        "reason": "CONFIG: Project metadata",
        "targetLocation": "docs/governance",
        "shouldMove": true,
        "action": "move",
        "fullSourcePath": "C:\\source\\repos\\bpm\\internal\\renderx-plugins-demo\\PROJECT_TAGS.json",
        "fullTargetPath": "C:\\source\\repos\\bpm\\internal\\renderx-plugins-demo\\docs\\governance\\PROJECT_TAGS.json"
      },
      {
        "filename": "REACT_COMPONENT_SELECTION_TRACE.json",
        "sourceLocation": ".",
        "classification": "domain-config",
        "domain": "react",
        "reason": "React component configuration",
        "targetLocation": "docs/react",
        "shouldMove": true,
        "action": "move",
        "fullSourcePath": "C:\\source\\repos\\bpm\\internal\\renderx-plugins-demo\\REACT_COMPONENT_SELECTION_TRACE.json",
        "fullTargetPath": "C:\\source\\repos\\bpm\\internal\\renderx-plugins-demo\\docs\\react\\REACT_COMPONENT_SELECTION_TRACE.json"
      },
      {
        "filename": "SHAPE_EVOLUTION_PLAN.json",
        "sourceLocation": ".",
        "classification": "domain-config",
        "domain": "shape",
        "reason": "Shape/evolution configuration",
        "targetLocation": "docs/shape",
        "shouldMove": true,
        "action": "move",
        "fullSourcePath": "C:\\source\\repos\\bpm\\internal\\renderx-plugins-demo\\SHAPE_EVOLUTION_PLAN.json",
        "fullTargetPath": "C:\\source\\repos\\bpm\\internal\\renderx-plugins-demo\\docs\\shape\\SHAPE_EVOLUTION_PLAN.json"
      },
      {
        "filename": "canvas_symphony_data.json",
        "sourceLocation": ".",
        "classification": "generated-data",
        "domain": null,
        "reason": "Generated symphony data",
        "targetLocation": "docs/search",
        "shouldMove": true,
        "action": "move",
        "fullSourcePath": "C:\\source\\repos\\bpm\\internal\\renderx-plugins-demo\\canvas_symphony_data.json",
        "fullTargetPath": "C:\\source\\repos\\bpm\\internal\\renderx-plugins-demo\\docs\\search\\canvas_symphony_data.json"
      },
      {
        "filename": "derived-external-interactions.json",
        "sourceLocation": ".",
        "classification": "unclassified",
        "domain": null,
        "reason": "Unclassified JSON file",
        "targetLocation": ".generated",
        "shouldMove": true,
        "action": "move",
        "fullSourcePath": "C:\\source\\repos\\bpm\\internal\\renderx-plugins-demo\\derived-external-interactions.json",
        "fullTargetPath": "C:\\source\\repos\\bpm\\internal\\renderx-plugins-demo\\.generated\\derived-external-interactions.json"
      },
      {
        "filename": "derived-external-topics.json",
        "sourceLocation": ".",
        "classification": "unclassified",
        "domain": null,
        "reason": "Unclassified JSON file",
        "targetLocation": ".generated",
        "shouldMove": true,
        "action": "move",
        "fullSourcePath": "C:\\source\\repos\\bpm\\internal\\renderx-plugins-demo\\derived-external-topics.json",
        "fullTargetPath": "C:\\source\\repos\\bpm\\internal\\renderx-plugins-demo\\.generated\\derived-external-topics.json"
      },
      {
        "filename": "eslint-report.json",
        "sourceLocation": ".",
        "classification": "unclassified",
        "domain": null,
        "reason": "Unclassified JSON file",
        "targetLocation": ".generated",
        "shouldMove": true,
        "action": "move",
        "fullSourcePath": "C:\\source\\repos\\bpm\\internal\\renderx-plugins-demo\\eslint-report.json",
        "fullTargetPath": "C:\\source\\repos\\bpm\\internal\\renderx-plugins-demo\\.generated\\eslint-report.json"
      },
      {
        "filename": "eslint-report3.json",
        "sourceLocation": ".",
        "classification": "unclassified",
        "domain": null,
        "reason": "Unclassified JSON file",
        "targetLocation": ".generated",
        "shouldMove": true,
        "action": "move",
        "fullSourcePath": "C:\\source\\repos\\bpm\\internal\\renderx-plugins-demo\\eslint-report3.json",
        "fullTargetPath": "C:\\source\\repos\\bpm\\internal\\renderx-plugins-demo\\.generated\\eslint-report3.json"
      },
      {
        "filename": "eslint-report4.json",
        "sourceLocation": ".",
        "classification": "unclassified",
        "domain": null,
        "reason": "Unclassified JSON file",
        "targetLocation": ".generated",
        "shouldMove": true,
        "action": "move",
        "fullSourcePath": "C:\\source\\repos\\bpm\\internal\\renderx-plugins-demo\\eslint-report4.json",
        "fullTargetPath": "C:\\source\\repos\\bpm\\internal\\renderx-plugins-demo\\.generated\\eslint-report4.json"
      },
      {
        "filename": "eslint-report5.json",
        "sourceLocation": ".",
        "classification": "unclassified",
        "domain": null,
        "reason": "Unclassified JSON file",
        "targetLocation": ".generated",
        "shouldMove": true,
        "action": "move",
        "fullSourcePath": "C:\\source\\repos\\bpm\\internal\\renderx-plugins-demo\\eslint-report5.json",
        "fullTargetPath": "C:\\source\\repos\\bpm\\internal\\renderx-plugins-demo\\.generated\\eslint-report5.json"
      },
      {
        "filename": "eslint-report6.json",
        "sourceLocation": ".",
        "classification": "unclassified",
        "domain": null,
        "reason": "Unclassified JSON file",
        "targetLocation": ".generated",
        "shouldMove": true,
        "action": "move",
        "fullSourcePath": "C:\\source\\repos\\bpm\\internal\\renderx-plugins-demo\\eslint-report6.json",
        "fullTargetPath": "C:\\source\\repos\\bpm\\internal\\renderx-plugins-demo\\.generated\\eslint-report6.json"
      },
      {
        "filename": "eslint-report7.json",
        "sourceLocation": ".",
        "classification": "unclassified",
        "domain": null,
        "reason": "Unclassified JSON file",
        "targetLocation": ".generated",
        "shouldMove": true,
        "action": "move",
        "fullSourcePath": "C:\\source\\repos\\bpm\\internal\\renderx-plugins-demo\\eslint-report7.json",
        "fullTargetPath": "C:\\source\\repos\\bpm\\internal\\renderx-plugins-demo\\.generated\\eslint-report7.json"
      },
      {
        "filename": "eslint-report8.json",
        "sourceLocation": ".",
        "classification": "unclassified",
        "domain": null,
        "reason": "Unclassified JSON file",
        "targetLocation": ".generated",
        "shouldMove": true,
        "action": "move",
        "fullSourcePath": "C:\\source\\repos\\bpm\\internal\\renderx-plugins-demo\\eslint-report8.json",
        "fullTargetPath": "C:\\source\\repos\\bpm\\internal\\renderx-plugins-demo\\.generated\\eslint-report8.json"
      },
      {
        "filename": "interaction-manifest.json",
        "sourceLocation": ".",
        "classification": "manifests",
        "domain": null,
        "reason": "Plugin/layout manifest",
        "targetLocation": "docs/manifests",
        "shouldMove": true,
        "action": "move",
        "fullSourcePath": "C:\\source\\repos\\bpm\\internal\\renderx-plugins-demo\\interaction-manifest.json",
        "fullTargetPath": "C:\\source\\repos\\bpm\\internal\\renderx-plugins-demo\\docs\\manifests\\interaction-manifest.json"
      },
      {
        "filename": "knowledge-index.json",
        "sourceLocation": ".",
        "classification": "generated-index",
        "domain": null,
        "reason": "Generated knowledge index",
        "targetLocation": "docs/search",
        "shouldMove": true,
        "action": "move",
        "fullSourcePath": "C:\\source\\repos\\bpm\\internal\\renderx-plugins-demo\\knowledge-index.json",
        "fullTargetPath": "C:\\source\\repos\\bpm\\internal\\renderx-plugins-demo\\docs\\search\\knowledge-index.json"
      },
      {
        "filename": "layout-manifest.json",
        "sourceLocation": ".",
        "classification": "manifests",
        "domain": null,
        "reason": "Plugin/layout manifest",
        "targetLocation": "docs/manifests",
        "shouldMove": true,
        "action": "move",
        "fullSourcePath": "C:\\source\\repos\\bpm\\internal\\renderx-plugins-demo\\layout-manifest.json",
        "fullTargetPath": "C:\\source\\repos\\bpm\\internal\\renderx-plugins-demo\\docs\\manifests\\layout-manifest.json"
      },
      {
        "filename": "orchestration-audit-system-project-plan.json",
        "sourceLocation": ".",
        "classification": "governance",
        "domain": null,
        "reason": "AUTHORITY: Project plan",
        "targetLocation": "docs/governance",
        "shouldMove": true,
        "action": "move",
        "fullSourcePath": "C:\\source\\repos\\bpm\\internal\\renderx-plugins-demo\\orchestration-audit-system-project-plan.json",
        "fullTargetPath": "C:\\source\\repos\\bpm\\internal\\renderx-plugins-demo\\docs\\governance\\orchestration-audit-system-project-plan.json"
      },
      {
        "filename": "orchestration-domains.json",
        "sourceLocation": ".",
        "classification": "governance",
        "domain": null,
        "reason": "CONFIG: Domain mapping",
        "targetLocation": "docs/governance",
        "shouldMove": true,
        "action": "move",
        "fullSourcePath": "C:\\source\\repos\\bpm\\internal\\renderx-plugins-demo\\orchestration-domains.json",
        "fullTargetPath": "C:\\source\\repos\\bpm\\internal\\renderx-plugins-demo\\docs\\governance\\orchestration-domains.json"
      },
      {
        "filename": "public-api.hash.json",
        "sourceLocation": ".",
        "classification": "generated-hash",
        "domain": null,
        "reason": "Generated API hash",
        "targetLocation": "docs/search",
        "shouldMove": true,
        "action": "move",
        "fullSourcePath": "C:\\source\\repos\\bpm\\internal\\renderx-plugins-demo\\public-api.hash.json",
        "fullTargetPath": "C:\\source\\repos\\bpm\\internal\\renderx-plugins-demo\\docs\\search\\public-api.hash.json"
      },
      {
        "filename": "react-component-context-with-publish.json",
        "sourceLocation": ".",
        "classification": "domain-config",
        "domain": "react",
        "reason": "React component configuration",
        "targetLocation": "docs/react",
        "shouldMove": true,
        "action": "move",
        "fullSourcePath": "C:\\source\\repos\\bpm\\internal\\renderx-plugins-demo\\react-component-context-with-publish.json",
        "fullTargetPath": "C:\\source\\repos\\bpm\\internal\\renderx-plugins-demo\\docs\\react\\react-component-context-with-publish.json"
      },
      {
        "filename": "react-component-context.json",
        "sourceLocation": ".",
        "classification": "domain-config",
        "domain": "react",
        "reason": "React component configuration",
        "targetLocation": "docs/react",
        "shouldMove": true,
        "action": "move",
        "fullSourcePath": "C:\\source\\repos\\bpm\\internal\\renderx-plugins-demo\\react-component-context.json",
        "fullTargetPath": "C:\\source\\repos\\bpm\\internal\\renderx-plugins-demo\\docs\\react\\react-component-context.json"
      },
      {
        "filename": "react-component-theme-toggle.json",
        "sourceLocation": ".",
        "classification": "domain-config",
        "domain": "react",
        "reason": "React component configuration",
        "targetLocation": "docs/react",
        "shouldMove": true,
        "action": "move",
        "fullSourcePath": "C:\\source\\repos\\bpm\\internal\\renderx-plugins-demo\\react-component-theme-toggle.json",
        "fullTargetPath": "C:\\source\\repos\\bpm\\internal\\renderx-plugins-demo\\docs\\react\\react-component-theme-toggle.json"
      },
      {
        "filename": "root-context.json",
        "sourceLocation": ".",
        "classification": "generated-context",
        "domain": null,
        "reason": "Generated context",
        "targetLocation": "docs/search",
        "shouldMove": true,
        "action": "move",
        "fullSourcePath": "C:\\source\\repos\\bpm\\internal\\renderx-plugins-demo\\root-context.json",
        "fullTargetPath": "C:\\source\\repos\\bpm\\internal\\renderx-plugins-demo\\docs\\search\\root-context.json"
      },
      {
        "filename": "shape-evolutions-allowlist.json",
        "sourceLocation": ".",
        "classification": "domain-config",
        "domain": "shape",
        "reason": "Shape/evolution configuration",
        "targetLocation": "docs/shape",
        "shouldMove": true,
        "action": "move",
        "fullSourcePath": "C:\\source\\repos\\bpm\\internal\\renderx-plugins-demo\\shape-evolutions-allowlist.json",
        "fullTargetPath": "C:\\source\\repos\\bpm\\internal\\renderx-plugins-demo\\docs\\shape\\shape-evolutions-allowlist.json"
      },
      {
        "filename": "shape-evolutions.json",
        "sourceLocation": ".",
        "classification": "domain-config",
        "domain": "shape",
        "reason": "Shape/evolution configuration",
        "targetLocation": "docs/shape",
        "shouldMove": true,
        "action": "move",
        "fullSourcePath": "C:\\source\\repos\\bpm\\internal\\renderx-plugins-demo\\shape-evolutions.json",
        "fullTargetPath": "C:\\source\\repos\\bpm\\internal\\renderx-plugins-demo\\docs\\shape\\shape-evolutions.json"
      },
      {
        "filename": "shape.budgets.json",
        "sourceLocation": ".",
        "classification": "domain-config",
        "domain": "shape",
        "reason": "Shape/evolution configuration",
        "targetLocation": "docs/shape",
        "shouldMove": true,
        "action": "move",
        "fullSourcePath": "C:\\source\\repos\\bpm\\internal\\renderx-plugins-demo\\shape.budgets.json",
        "fullTargetPath": "C:\\source\\repos\\bpm\\internal\\renderx-plugins-demo\\docs\\shape\\shape.budgets.json"
      },
      {
        "filename": "topics-manifest.json",
        "sourceLocation": ".",
        "classification": "manifests",
        "domain": null,
        "reason": "Plugin/layout manifest",
        "targetLocation": "docs/manifests",
        "shouldMove": true,
        "action": "move",
        "fullSourcePath": "C:\\source\\repos\\bpm\\internal\\renderx-plugins-demo\\topics-manifest.json",
        "fullTargetPath": "C:\\source\\repos\\bpm\\internal\\renderx-plugins-demo\\docs\\manifests\\topics-manifest.json"
      }
    ],
    "keep-in-root": [
      {
        "filename": "package-lock.json",
        "sourceLocation": ".",
        "classification": "build-config",
        "domain": null,
        "reason": "Build/runtime configuration",
        "targetLocation": ".",
        "shouldMove": false,
        "action": "keep-in-root",
        "fullSourcePath": "C:\\source\\repos\\bpm\\internal\\renderx-plugins-demo\\package-lock.json",
        "fullTargetPath": "C:\\source\\repos\\bpm\\internal\\renderx-plugins-demo\\package-lock.json"
      },
      {
        "filename": "package.json",
        "sourceLocation": ".",
        "classification": "build-config",
        "domain": null,
        "reason": "Build/runtime configuration",
        "targetLocation": ".",
        "shouldMove": false,
        "action": "keep-in-root",
        "fullSourcePath": "C:\\source\\repos\\bpm\\internal\\renderx-plugins-demo\\package.json",
        "fullTargetPath": "C:\\source\\repos\\bpm\\internal\\renderx-plugins-demo\\package.json"
      },
      {
        "filename": "tsconfig.base.json",
        "sourceLocation": ".",
        "classification": "build-config",
        "domain": null,
        "reason": "Build/runtime configuration",
        "targetLocation": ".",
        "shouldMove": false,
        "action": "keep-in-root",
        "fullSourcePath": "C:\\source\\repos\\bpm\\internal\\renderx-plugins-demo\\tsconfig.base.json",
        "fullTargetPath": "C:\\source\\repos\\bpm\\internal\\renderx-plugins-demo\\tsconfig.base.json"
      },
      {
        "filename": "tsconfig.json",
        "sourceLocation": ".",
        "classification": "build-config",
        "domain": null,
        "reason": "Build/runtime configuration",
        "targetLocation": ".",
        "shouldMove": false,
        "action": "keep-in-root",
        "fullSourcePath": "C:\\source\\repos\\bpm\\internal\\renderx-plugins-demo\\tsconfig.json",
        "fullTargetPath": "C:\\source\\repos\\bpm\\internal\\renderx-plugins-demo\\tsconfig.json"
      }
    ]
  },
  "recommendations": [
    "Move 31 JSON files to proper domains and folders"
  ]
}