{
  "pluginId": "CanvasComponentResizeMovePlugin",
  "id": "canvas-component-resize-move-symphony",
  "name": "Canvas Component Resize Move",
  "movements": [
    {
      "id": "resize-move",
      "name": "Resize Move",
      "beats": [
        { "beat": 1, "event": "canvas:component:resize:move", "title": "Resize Move", "dynamics": "mf", "handler": "updateSize", "timing": "immediate", "kind": "stage-crew" },
        { "beat": 2, "event": "canvas:component:resize:forward", "title": "Forward to Control Panel", "dynamics": "mf", "handler": "forwardToControlPanel", "timing": "immediate", "kind": "pure" }
      ]
    }
  ]
}

